LICENSE
MANIFEST.in
README.md
requirements.txt
setup.cfg
setup.py
test-requirements.txt
tox.ini
version.info
contrail_api_client.egg-info/PKG-INFO
contrail_api_client.egg-info/SOURCES.txt
contrail_api_client.egg-info/dependency_links.txt
contrail_api_client.egg-info/requires.txt
contrail_api_client.egg-info/top_level.txt
etc/contrail/vnc_api_lib.ini
vnc_api/__init__.py
vnc_api/exceptions.py
vnc_api/ssl_adapter.py
vnc_api/utils.py
vnc_api/vnc_api.py
vnc_api/gen/__init__.py
vnc_api/gen/cfixture.py
vnc_api/gen/connection_drv_gen.py
vnc_api/gen/generatedssuper.py
vnc_api/gen/resource_client.py
vnc_api/gen/resource_common.py
vnc_api/gen/resource_test.py
vnc_api/gen/resource_xsd.py
vnc_api/gen/vnc_api_client_gen.py
vnc_api/gen/vnc_api_extension_gen.py
vnc_api/gen/vnc_api_schema.py
vnc_api/gen/vnc_api_test_gen.py
vnc_api/gen/heat/__init__.py
vnc_api/gen/heat/env/__init__.py
vnc_api/gen/heat/resources/__init__.py
vnc_api/gen/heat/resources/access_control_list_heat.py
vnc_api/gen/heat/resources/address_group_heat.py
vnc_api/gen/heat/resources/alarm_heat.py
vnc_api/gen/heat/resources/alias_ip_heat.py
vnc_api/gen/heat/resources/alias_ip_pool_heat.py
vnc_api/gen/heat/resources/analytics_alarm_node_heat.py
vnc_api/gen/heat/resources/analytics_node_heat.py
vnc_api/gen/heat/resources/analytics_snmp_node_heat.py
vnc_api/gen/heat/resources/api_access_list_heat.py
vnc_api/gen/heat/resources/application_policy_set_heat.py
vnc_api/gen/heat/resources/bgp_as_a_service_heat.py
vnc_api/gen/heat/resources/bgp_router_heat.py
vnc_api/gen/heat/resources/bgpvpn_heat.py
vnc_api/gen/heat/resources/bridge_domain_heat.py
vnc_api/gen/heat/resources/card_heat.py
vnc_api/gen/heat/resources/config_database_node_heat.py
vnc_api/gen/heat/resources/config_node_heat.py
vnc_api/gen/heat/resources/config_root_heat.py
vnc_api/gen/heat/resources/control_node_zone_heat.py
vnc_api/gen/heat/resources/customer_attachment_heat.py
vnc_api/gen/heat/resources/data_center_interconnect_heat.py
vnc_api/gen/heat/resources/database_node_heat.py
vnc_api/gen/heat/resources/device_image_heat.py
vnc_api/gen/heat/resources/devicemgr_node_heat.py
vnc_api/gen/heat/resources/discovery_service_assignment_heat.py
