Metadata-Version: 1.1
Name: contrail-api-client
Version: 5.1.0
Summary: Contrail VNC Configuration API client library
Home-page: http://www.opencontrail.org/documentation/api/r4.1/
Author: OpenContrail
Author-email: dev@lists.opencontrail.org
License: Apache-2
Keywords: contrail vnc api client library
Platform: UNKNOWN
Classifier: Intended Audience :: Information Technology
Classifier: Intended Audience :: Developers
Classifier: Intended Audience :: System Administrators
Classifier: License :: OSI Approved :: Apache Software License
Classifier: Operating System :: POSIX :: Linux
Classifier: Development Status :: 5 - Production/Stable
Classifier: Programming Language :: Python
Classifier: Programming Language :: Python :: 2
Classifier: Programming Language :: Python :: 2.7
